algoMain.py
algomain-1.0.0.dist-info/METADATA
algomain-1.0.0.dist-info/WHEEL
algomain-1.0.0.dist-info/RECORD
