Metadata-Version: 2.1
Name: algomain
Version: 1.0.0
Summary: Library calling basic algorithms
Author: Sere221
Author-email: 131906243+Sere221@users.noreply.github.com
Requires-Python: >=3.8,<4.0
Classifier: Programming Language :: Python :: 3
Classifier: Programming Language :: Python :: 3.8
Classifier: Programming Language :: Python :: 3.9
Classifier: Programming Language :: Python :: 3.10
Classifier: Programming Language :: Python :: 3.11
Classifier: Programming Language :: Python :: 3.12
Requires-Dist: pendulum (>=3.0.0,<4.0.0)
